Verilog_V1/Median_Filter.v
/////////////////////////////////////////////////////////////////////////////
//
// @brief: Verilog Implementatin of the Median Filter: This Module
//			Is final stage in implementing the median filter.
//
// @version: 0.0.1
// @Date: 09/05/2024
// @filename: Median_Filter.v
//
//
// @authors: 
///////////////////////////////////////////////////////////////////////////////////////////


module Median_Filter(
/////////////////////Control Ports///////////////////////////////////////////////

Filter_CLK,Filter_RST, 

///////////////////Index_Tracker Interfacing Ports///////////////////////////////

 Filter_EN,Filter_sROW, Filter_sCOL, Filter_OUT, Filter_FILTDRDY,

 ///////////////////Memory Interfacing Ports////////////////////////////////////

 Filter_MEMDR, Filter_MEMADDR, Filter_MEMREAD, Filter_MEMDRDY

 );

 //------------------------------------------------------------------------------------------------//
 //								MEDIAN FILTER PARAMETERS
 //------------------------------------------------------------------------------------------------//

parameter WINDOW_SIZE = 3; //Defaults to window size fo 3x3
parameter DATA_WIDTH = 24; // defult RGB pixel width
parameter BUS_WIDTH = 32; //same as Memory.v module
parameter IMG_WIDTH = 512;

//----------------------------------------------------------------------------------------------------------------//
//								FILTER PORTS
//----------------------------------------------------------------------------------------------------------------//

//Control Ports

input Filter_RST ; // Filter reset line.

input Filter_CLK; // Filter clock signal (for synchronized operations)

//Index_Tracker Interfacning ports

input [BUS_WIDTH-1:0] Filter_sROW; // Index of the row number where the filter window starts
input [BUS_WIDTH-1:0] Filter_sCOL; // Index of the column number where the window starts
input Filter_EN; // Filter Enable Line: image processed only when this line is HIGH
output reg [DATA_WIDTH-1:0] Filter_OUT; // Resultig Filter pixel of the window.
output reg Filter_FILTDRDY; // Signaling line that a single pixel has been processed.

//Memory Interfacing ports

input [DATA_WIDTH-1:0] Filter_MEMDR; // Pixel Data from the memory: this is the pixel within the filter window.
input Filter_MEMDRDY; // Memory Data Ready Line.
output reg [BUS_WIDTH-1:0] Filter_MEMADDR;
output reg [1:0] Filter_MEMREAD;

/////////////////////////////////INTERNAL REGISTERS//////////////////////////////////////////////////////////

reg [15:0] Filter_SR; // Filter status Register
// Iterators
integer row;
integer col;
integer i;
reg started;
integer wind_indx; // keeps index of the window where insertion should be made

reg [DATA_WIDTH-1:0] window [0:WINDOW_SIZE*WINDOW_SIZE-1]; // Convolution window of the filter

////////////////////////////////////////////////////////////////////////////////////////////////////////////

//Function that sorts the elements in window buffer, uses bubble sort
function sortWindow(input integer mxm);
	reg [ DATA_WIDTH-1:0] temp;
	integer k, j ; // iterators
	begin
		for( k = 0;k< WINDOW_SIZE*WINDOW_SIZE-1; k= k+1) begin
			for(j=0; j < WINDOW_SIZE*WINDOW_SIZE-1-k; j= j+1) begin
				if(window[j] > window[j+1]) begin
					temp = window[j];
					window[j] = window[j+1];
					window[j+1] = temp;
				end
			end
		end
		sortWindow =0;
	end

endfunction


//////////////////////////////////////MODULE IMPLEMENTATION///////////////////////////////////////////////

always@(posedge Filter_CLK) begin		
		if(Filter_RST) begin
			row <=0;
			col <=0;
			i <=0;
			wind_indx <=0;
			for(wind_indx = 0; wind_indx < WINDOW_SIZE*WINDOW_SIZE ; wind_indx++) begin
				window[wind_indx] <=0;
			end
			Filter_OUT <=0;
			Filter_FILTDRDY <=0;
			Filter_MEMADDR <=0;
			Filter_MEMREAD <=0;
		end
end

//at the start of each window read request
always@(posedge Filter_EN) begin
	Filter_SR[15:14] <= 2'b01; // set mode to READ_WINDOW
	row <= Filter_sROW; // row number f the first pixel in the convolution window
	col <= Filter_sCOL; //
	Filter_MEMADDR <= row*IMG_WIDTH + col; // 
end

//Handle MEMORY DATA READY REQUESTS.

always@(negedge Filter_MEMDRDY) begin
	// Check to see if the  filter is still enabled
	if(Filter_EN==1 && Filter_SR[15:14] == 1) begin
		if(i>=WINDOW_SIZE*WINDOW_SIZE-1) begin
			i = 0; // reset the window size_tracker
			Filter_SR[15:14] = 2'b10; // set the status to 2: WINDW_READY: this propts for sorting and computation of the median
			Filter_MEMREAD = 0;
		end else begin
			//add the value the current index from the window:
			window[i] = Filter_MEMDR; // Read the data on the Memory Data Bus, and store it  in the window
			
			if((i+1)%(WINDOW_SIZE)==0 && i!=0) begin
				row = row + 1;
				col = Filter_sCOL;
				i = i+1;
			end else begin
				col = col+1;
				i = i+1;
			end
			Filter_MEMADDR= row*IMG_WIDTH + col; //get address of the next pixel.
		end
	end // otherwise igore this trigger it isn't meant for you
end

always@(negedge Filter_CLK) begin

	if(Filter_SR[15:14] == 1 && Filter_EN ==1) begin
		Filter_MEMREAD = 2; // Promt for memory read.
	end 

	else if(Filter_SR[15:14] == 2) begin
		//Sort the window
		i=sortWindow(0); // THis function will sort the window.
		//when obtain the 
		Filter_OUT = window[(WINDOW_SIZE*WINDOW_SIZE)/2]; // Median  is at the middle of the window.
		Filter_FILTDRDY = 1; // set filter data ready.
		Filter_SR[15:14] = 0; // set the status to WAIT_FOR_NEW_WINDOW  or IDLE
		Filter_MEMREAD = 0;
	end else if(Filter_SR[15:14] ==0) begin

		Filter_FILTDRDY = 0;

	end

end


endmodule

Verilog_V1/Memory.v
//////////////////////////////////////////////////////////////////////////////////////////////////
//																								
// @brief: Memory module that stores image pixels during porcessing		
// Date: 08/05/2024											
// Version: v0													
// Filename: Memory.v														
//														
//Project: FPGA Implementation of a median filter							
//Authors:											
//															
//////////////////////////////////////////////////////////////////////////////////////////////////

`timescale 1ns/1ps

module Memory(Mem_CLK, Mem_RST, Mem_RW, Mem_ADDR, Mem_IDR, Mem_ODR, Mem_DRDY);

//----------------------------------------------------------------------------------------------//
//				MEMORY PARAMETERS                            
//----------------------------------------------------------------------------------------------//

parameter DATA_WIDTH = 24; // Defualts to 24-bits ( for threee chanel image)

parameter DEPTH = 512*512; // Defaults to 512*512 pixels ( maximum size of images to be processed)

parameter ADDR_WIDTH = 32; //Width of the address, defaults to 32-bit bus address

parameter FILENAME = "test_hex.txt";

//----------------------------------------------------------------------------------------------//
//				MEMORY PORT DECLARATION															
//----------------------------------------------------------------------------------------------//
 input Mem_CLK; //Input Clock
 input Mem_RST; //Reset line
 input [1:0] Mem_RW; // read or write selection line
 input [DATA_WIDTH-1:0] Mem_IDR; // Memory Input Data ( the Write Data)
 output  reg [DATA_WIDTH-1:0] Mem_ODR; // Memory Output Data ( read data)
 output reg Mem_DRDY; // Memory Data ready flag.
 input [ADDR_WIDTH-1:0] Mem_ADDR;

//----------------------------------------------------------------------------------------------//
//							MEMORY INTERNAL REGISTERS			
//----------------------------------------------------------------------------------------------//

reg [DATA_WIDTH-1:0] MEMORY [0:DEPTH-1]; //MEMORY  BLOCK

//----------------------------------------------------------------------------------------------//
///						MODULE IMPLEMENTATION
//----------------------------------------------------------------------------------------------//

////////////////////////////////ITERATIRS/////////////////////////////////////////////////////////

integer iter;

always@(posedge Mem_CLK) begin
	
	//Reset
	if(Mem_RST) begin
		$readmemh(FILENAME,MEMORY); //reads Data from Memory.
		Mem_ODR <= 0;
		Mem_DRDY <=0;
	end else if(Mem_RW == 2'b01) begin
		MEMORY[Mem_ADDR] <= Mem_IDR;
	end else if(Mem_RW == 2'b10) begin
		Mem_ODR<= MEMORY[Mem_ADDR];
		Mem_DRDY<= 1;
	end else if(Mem_RW == 2'b11) begin
		$readmemh(FILENAME,MEMORY); //reads Data from Memory.
		Mem_DRDY <= 1; //Notify that Data Is Ready(has been read)
	end

end

//Clear the ready flag on the next falling edge
always@(negedge Mem_CLK) begin
	Mem_DRDY <= 0;
end

endmodule

Verilog_V1/Coordinator.v
///////////////////////////////////////////////////////////////////////////////////////
//
// @brief: Coordinates the median filtering process, by keeping track of 
//			the address of the pixel in image being filtered, as well
//			filtering results should be written.
//
// @version: 0.0.1
// @authors: Kananelo Chabeli
//
/////////////////////////////////////////////////////////////////////////////////////

module Coordinator(Coordinator_CLK, Coordinator_RST,Coordinator_STRT, Coordinator_MUXSEL, Coordinator_sROW, Coordinator_sCOL, Coordinator_FEN, Coordinator_DRDY, Coordinator_MEMADDR, Coordinator_MEMW, Coordinator_DNE);

////////////////////////////////////////////////////////////////////////////////////////////////////////
//									MODULE PARAMETERS
////////////////////////////////////////////////////////////////////////////////////////////////////////

parameter DATA_WIDTH = 24;
parameter BUS_WIDTH = 32;
parameter WINDOW_SIZE = 3;
parameter IMG_WIDTH = 512;
parameter IMG_HEIGHT = 512;

////////////////////////////////////////////////////////////////////////////////////////////////////
//									MODULE PORT DECLARATIONS
/////////////////////////////////////////////////////////////////////////////////////////////////////

input Coordinator_STRT; // Filter start signal  ()
input Coordinator_CLK; // input Clock
input Coordinator_RST; // Reset Line.
output reg [BUS_WIDTH-1:0] Coordinator_sROW; //row number where the filter window starts.
output reg [BUS_WIDTH-1:0] Coordinator_sCOL; //column number where the filter window starts
output reg Coordinator_FEN; // Filter Enable signal: must be kept high till filter is done filtering curren pixel

output reg Coordinator_MUXSEL; // Multiplexor Selection Line

input wire Coordinator_DRDY; // Signal sent  by the filter that results is ready.
output reg [BUS_WIDTH-1:0] Coordinator_MEMADDR; // Memory Address where the resulting pixel is written
output reg [1:0] Coordinator_MEMW; // Memory Read/ Write selection line: This module can only write to memory
output reg Coordinator_DNE; // Signal that Filtering has been completed.

/////////////////////////////////////////////////////////////////////////////////////////////////////////////////
//									MODULE INTERNAL REGISTERS
/////////////////////////////////////////////////////////////////////////////////////////////////////////////////

reg [1:0] Coordinator_SR; // Status regsier, to keep track of when to make decisions

integer RES_STRT_ADDR;// Address where the resulting image starts
integer currRow; // row number of the current pixel being filtered
integer currCol; // column number of the pixel being filtered
integer  i; // Iterators ( keep track f how many pixels have been processed already.)

/////////////////////////////////////////////////////////////////////////////////////////////////////////////////
//									MODULE IMPLEMENTATION					
/////////////////////////////////////////////////////////////////////////////////////////////////////////////////

always@(posedge Coordinator_CLK or posedge Coordinator_STRT) begin

	if(Coordinator_RST) begin
		Coordinator_MEMADDR <= 0;
		Coordinator_MEMW <=0;
		Coordinator_FEN <=0;
		Coordinator_DNE <=0;
		Coordinator_sROW <=0;
		Coordinator_sCOL <=0;
		Coordinator_SR <=0;
		Coordinator_MUXSEL <=0;
		RES_STRT_ADDR <= (IMG_WIDTH+WINDOW_SIZE-1)*(IMG_HEIGHT+WINDOW_SIZE - 1);
		currRow <= WINDOW_SIZE/2;
		currCol <= WINDOW_SIZE/2;
	end else if(Coordinator_STRT) begin
		Coordinator_SR <= 1; // Set Execution mode to: SEND_WINDOW_DETAILS
		i <=0;//pixel counter start at zer
		
	end
end

always@(negedge Coordinator_CLK) begin
	if(Coordinator_SR == 1) begin
		Coordinator_MUXSEL<=0;
		Coordinator_FEN <= 1;
		Coordinator_SR <=0; // Change mode to IDLE: (while waiting for filter to perform its filtering prcess)
		Coordinator_sROW <= currRow-(WINDOW_SIZE/2);// row coordinate of the pixel at start of the window.
		Coordinator_sCOL <= currCol-(WINDOW_SIZE/2); // col number of the pixel at the start f the window.
		//Coordinator_MEMW <=2;
	end else if(Coordinator_SR == 2) begin
		Coordinator_DNE <= 1;
		Coordinator_MEMADDR <= RES_STRT_ADDR; // Set the memory address of the starting of the result image
	end else if(Coordinator_SR == 0) begin
		Coordinator_DNE <= 0; // Keep DNE line low, always
	end
end

always@(posedge Coordinator_DRDY) begin	
	Coordinator_FEN = 0; // lower your filter enable line.
	Coordinator_MEMADDR = RES_STRT_ADDR + (currRow-(WINDOW_SIZE/2)*IMG_WIDTH+currCol-(WINDOW_SIZE/2));
	Coordinator_MEMW = 1; // send the write signal to memory
	Coordinator_MUXSEL = 1;

	if(i>=IMG_WIDTH*IMG_HEIGHT -1) begin
		//that was the last pixel filter, so send mode to DONE
		Coordinator_SR = 2; // DONE
		i =0; // reset iterators
		currCol = WINDOW_SIZE;
		currRow = WINDOW_SIZE;
	end 
	//Otherwise adjust coefficients
	else if((i+1)%IMG_WIDTH == 0 && i!=0) begin
			currRow = currRow+1;
			currCol = WINDOW_SIZE/2;
			i = i +1;
			Coordinator_SR = 1;
	end else begin
		currCol = currCol + 1;
		i = i + 1;
		Coordinator_SR = 1;
	end

	//check to
end

endmodule

Verilog_V1/TwoInputMultiplexor.v
/**

@brief: A multiplexor selects is a combinational circuit that selects 
one input from in from multiple inputs


@author: Kananelo Chabeli
**/

module TwoInputMultiplexor(Input1,Input2,Select,Output);

//-------------------------------------MODULE PARAMETER--------------------------------------//
parameter DATA_WIDTH = 24; // data width set to a pixel width by default.

//-------------------------------------MODULE PORT DECLARTATION------------------------------//
input wire [DATA_WIDTH-1:0] Input1;
input wire [DATA_WIDTH-1:0] Input2;
input wire Select;
output reg [DATA_WIDTH-1:0] Output;
//--------------------------------------MODULE IMPLEMENTATIONS-----------------------------//
always@(*) begin
	if(Select) begin
		Output = Input1;
	end else begin
		Output = Input2;
	end
end
//-------------------------------------END OF MODULE---------------------------------------//

endmodule

Verilog_V1/filterTB.v
//Testbench for Median_Filter module

`timescale 1ns/1ps

module windowReadTB();

//parameters

parameter WINDOW_WIDTH = 3;
parameter DATA_DEPTH = 81+49;
parameter DATA_WIDTH = 16;
parameter IMG_WIDTH = 9;
parameter IMG_HEIGHT = 9;
parameter BUS_WIDTH = 8;

// varianbles

reg clk, rst;
wire [1:0] rw;
wire [1:0] coordRW;
wire [1:0] filtRW;

wire [BUS_WIDTH-1:0]mem_addr;
wire [DATA_WIDTH-1:0] mem_odata;
wire [DATA_WIDTH-1:0] mem_idata;
wire mem_drdy;

wire [BUS_WIDTH-1:0] sROW;
wire [BUS_WIDTH-1:0] coordAddr;
wire [BUS_WIDTH-1:0] FiltAddr;
wire filt_en;
wire [BUS_WIDTH-1:0] sCOL;
reg strt;
wire filt_rdy;
wire dne;
wire sel;

//Multiplexor Instances

TwoInputMultiplexor #(.DATA_WIDTH(BUS_WIDTH)) addressMUX(coordAddr,FiltAddr,sel,mem_addr);

TwoInputMultiplexor #(.DATA_WIDTH(2)) readwriteMUX(coordRW,filtRW,sel,rw);



// Coordinator(Coordinator_CLK, Coordinator_RST,Coordinator_STRT, Coordinator_sROW, Coordinator_sCOL, Coordinator_FEN, Coordinator_DRDY, Coordinator_MEMADDR, Coordinator_MEMW, Coordinator_DNE);


//Coordinator Instance

Coordinator #(.DATA_WIDTH(DATA_WIDTH), .BUS_WIDTH(BUS_WIDTH), .WINDOW_SIZE(WINDOW_WIDTH),.IMG_WIDTH(7), .IMG_HEIGHT(7))
coordinator(clk,rst,strt,sel,sROW, sCOL,filt_en,filt_rdy,coordAddr,coordRW,dne);


//module Memory(Mem_CLK, Mem_RST, Mem_RW, Mem_ADDR, Mem_IDR, Mem_ODR, Mem_DRDY);
//Instatiate the memory module.

Memory #(.DATA_WIDTH(DATA_WIDTH), .ADDR_WIDTH(BUS_WIDTH), .DEPTH(DATA_DEPTH)) memory
(clk, rst, rw, mem_addr, mem_idata, mem_odata, mem_drdy);

//Instantiate the Median_Filter module

Median_Filter #(.WINDOW_SIZE(WINDOW_WIDTH), .DATA_WIDTH(DATA_WIDTH), .BUS_WIDTH(BUS_WIDTH), .IMG_WIDTH(IMG_WIDTH))
filter(clk,rst,filt_en, sROW, sCOL, mem_idata, filt_rdy,mem_odata, FiltAddr,filtRW,mem_drdy);

initial begin

	$dumpfile("filterDump.vcd");
	$dumpvars(0, windowReadTB);
	$monitor($time,"  CLK:%b  RST:%b STRT:%b FILTER_ENABLE:%b R/W:%b ADDR:%x  oData:%x   iData:%x MemRDY:%b FiltRDY:%b",
	clk,rst,strt,filt_en,rw,mem_addr,mem_odata,mem_idata, mem_drdy, filt_rdy);
	
	clk =0; rst=0;strt =0;

	// reset the modules
	#4 rst = 1;
	#2 rst = 0; 
	#3 strt = 1; // enable the window
	#4 strt = 0;
	#1000 $finish; 
end

always begin
	#1 clk = ~clk;
end
endmodule

Verilog_V1/filterDump.vcd
$date
	Sun May 12 08:59:00 2024
$end
$version
	Icarus Verilog
$end
$timescale
	1ps
$end
$scope module windowReadTB $end
$var wire 1 ! sel $end
$var wire 8 " sROW [7:0] $end
$var wire 8 # sCOL [7:0] $end
$var wire 2 $ rw [1:0] $end
$var wire 16 % mem_odata [15:0] $end
$var wire 16 & mem_idata [15:0] $end
$var wire 1 ' mem_drdy $end
$var wire 8 ( mem_addr [7:0] $end
$var wire 1 ) filt_rdy $end
$var wire 1 * filt_en $end
$var wire 2 + filtRW [1:0] $end
$var wire 1 , dne $end
$var wire 2 - coordRW [1:0] $end
$var wire 8 . coordAddr [7:0] $end
$var wire 8 / FiltAddr [7:0] $end
$var reg 1 0 clk $end
$var reg 1 1 rst $end
$var reg 1 2 strt $end
$scope module addressMUX $end
$var wire 1 ! Select $end
$var wire 8 3 Input2 [7:0] $end
$var wire 8 4 Input1 [7:0] $end
$var reg 8 5 Output [7:0] $end
$upscope $end
$scope module coordinator $end
$var wire 1 0 Coordinator_CLK $end
$var wire 1 1 Coordinator_RST $end
$var wire 1 2 Coordinator_STRT $end
$var wire 1 ) Coordinator_DRDY $end
$var reg 1 , Coordinator_DNE $end
$var reg 1 * Coordinator_FEN $end
$var reg 8 6 Coordinator_MEMADDR [7:0] $end
$var reg 2 7 Coordinator_MEMW [1:0] $end
$var reg 1 ! Coordinator_MUXSEL $end
$var reg 2 8 Coordinator_SR [1:0] $end
$var reg 8 9 Coordinator_sCOL [7:0] $end
$var reg 8 : Coordinator_sROW [7:0] $end
$var integer 32 ; RES_STRT_ADDR [31:0] $end
$var integer 32 < currCol [31:0] $end
$var integer 32 = currRow [31:0] $end
$var integer 32 > i [31:0] $end
$upscope $end
$scope module filter $end
$var wire 1 0 Filter_CLK $end
$var wire 1 * Filter_EN $end
$var wire 1 1 Filter_RST $end
$var wire 8 ? Filter_sCOL [7:0] $end
$var wire 8 @ Filter_sROW [7:0] $end
$var wire 1 ' Filter_MEMDRDY $end
$var wire 16 A Filter_MEMDR [15:0] $end
$var reg 1 ) Filter_FILTDRDY $end
$var reg 8 B Filter_MEMADDR [7:0] $end
$var reg 2 C Filter_MEMREAD [1:0] $end
$var reg 16 D Filter_OUT [15:0] $end
$var reg 16 E Filter_SR [15:0] $end
$var integer 32 F col [31:0] $end
$var integer 32 G i [31:0] $end
$var integer 32 H row [31:0] $end
$var integer 32 I wind_indx [31:0] $end
$scope function sortWindow $end
$var reg 16 J temp [15:0] $end
$var integer 32 K j [31:0] $end
$var integer 32 L k [31:0] $end
$var integer 32 M mxm [31:0] $end
$upscope $end
$upscope $end
$scope module memory $end
$var wire 8 N Mem_ADDR [7:0] $end
$var wire 1 0 Mem_CLK $end
$var wire 16 O Mem_IDR [15:0] $end
$var wire 1 1 Mem_RST $end
$var wire 2 P Mem_RW [1:0] $end
$var reg 1 ' Mem_DRDY $end
$var reg 16 Q Mem_ODR [15:0] $end
$upscope $end
$scope module readwriteMUX $end
$var wire 2 R Input1 [1:0] $end
$var wire 2 S Input2 [1:0] $end
$var wire 1 ! Select $end
$var reg 2 T Output [1:0] $end
$upscope $end
$upscope $end
$enddefinitions $end
#0
$dumpvars
bx T
bx S
bx R
bx Q
bx P
bx O
bx N
bx M
bx L
bx K
bx J
bx I
bx H
bx G
bx F
bx E
bx D
bx C
bx B
bx A
bx @
bx ?
bx >
bx =
bx <
bx ;
bx :
bx 9
bx 8
bx 7
bx 6
bx 5
bx 4
bx 3
02
01
00
bx /
bx .
bx -
x,
bx +
x*
x)
bx (
0'
bx &
bx %
bx $
bx #
bx "
x!
$end
#1000
10
#2000
00
#3000
10
#4000
00
11
#5000
b0 $
b0 P
b0 T
b0 (
b0 5
b0 N
b1 <
b1 =
b1010001 ;
0!
b0 8
b0 #
b0 9
b0 ?
b0 "
b0 :
b0 @
0,
0*
b0 -
b0 7
b0 R
b0 .
b0 4
b0 6
b0 %
b0 A
b0 Q
b0 +
b0 C
b0 S
b0 /
b0 3
b0 B
0)
b0 &
b0 D
b0 O
b0 G
b0 F
b0 H
b0 I
10
#6000
00
01
#7000
10
#8000
00
#9000
b0 >
b1 8
10
12
#10000
b1xxxxxxxxxxxxxx E
b0 8
1*
00
#11000
b1 8
10
#12000
b0 8
b10 $
b10 P
b10 T
b10 +
b10 C
b10 S
00
#13000
1'
10
02
#14000
b1 (
b1 5
b1 N
b1 /
b1 3
b1 B
b1 G
b1 F
0'
00
#15000
1'
10
#16000
b10 (
b10 5
b10 N
b10 /
b10 3
b10 B
b10 G
b10 F
0'
00
#17000
1'
10
#18000
b1001 (
b1001 5
b1001 N
b1001 /
b1001 3
b1001 B
b11 G
b0 F
b1 H
0'
00
#19000
1'
10
#20000
b1010 (
b1010 5
b1010 N
b1010 /
b1010 3
b1010 B
b100 G
b1 F
0'
00
#21000
1'
b1101111111100001 %
b1101111111100001 A
b1101111111100001 Q
10
#22000
b1011 (
b1011 5
b1011 N
b1011 /
b1011 3
b1011 B
b101 G
b10 F
0'
00
#23000
1'
b10001111101101 %
b10001111101101 A
b10001111101101 Q
10
#24000
b10010 (
b10010 5
b10010 N
b10010 /
b10010 3
b10010 B
b110 G
b0 F
b10 H
0'
00
#25000
1'
b0 %
b0 A
b0 Q
10
#26000
b10011 (
b10011 5
b10011 N
b10011 /
b10011 3
b10011 B
b111 G
b1 F
0'
00
#27000
1'
b11010001011111 %
b11010001011111 A
b11010001011111 Q
10
#28000
b10100 (
b10100 5
b10100 N
b10100 /
b10100 3
b10100 B
b1000 G
b10 F
0'
00
#29000
1'
b1111001101000010 %
b1111001101000010 A
b1111001101000010 Q
10
#30000
b0 $
b0 P
b0 T
b0 +
b0 C
b0 S
b10xxxxxxxxxxxxxx E
b0 G
0'
00
#31000
10
#32000
b1 $
b1 P
b1 T
b1001011 (
b1001011 5
b1001011 N
b1 8
b1 >
b10 <
1!
b1 -
b1 7
b1 R
b1001011 .
b1001011 4
b1001011 6
0*
b0xxxxxxxxxxxxxx E
1)
b10001111101101 J
b1 K
b1000 L
b0 M
00
#33000
10
#34000
b1 F
b0 H
b1xxxxxxxxxxxxxx E
b10100 (
b10100 5
b10100 N
b0 $
b0 P
b0 T
b1 #
b1 9
b1 ?
b0 8
1*
0!
0)
00
#35000
10
#36000
b10 $
b10 P
b10 T
b10 +
b10 C
b10 S
00
#37000
1'
10
#38000
b10 (
b10 5
b10 N
b10 /
b10 3
b10 B
b1 G
b10 F
0'
00
#39000
1'
b0 %
b0 A
b0 Q
10
#40000
b11 (
b11 5
b11 N
b11 /
b11 3
b11 B
b10 G
b11 F
0'
00
#41000
1'
10
#42000
b1010 (
b1010 5
b1010 N
b1010 /
b1010 3
b1010 B
b11 G
b1 F
b1 H
0'
00
#43000
1'
b1101111111100001 %
b1101111111100001 A
b1101111111100001 Q
10
#44000
b1011 (
b1011 5
b1011 N
b1011 /
b1011 3
b1011 B
b100 G
b10 F
0'
00
#45000
1'
b10001111101101 %
b10001111101101 A
b10001111101101 Q
10
#46000
b1100 (
b1100 5
b1100 N
b1100 /
b1100 3
b1100 B
b101 G
b11 F
0'
00
#47000
1'
b1110110111101111 %
b1110110111101111 A
b1110110111101111 Q
10
#48000
b10011 (
b10011 5
b10011 N
b10011 /
b10011 3
b10011 B
b110 G
b1 F
b10 H
0'
00
#49000
1'
b11010001011111 %
b11010001011111 A
b11010001011111 Q
10
#50000
b10100 (
b10100 5
b10100 N
b10100 /
b10100 3
b10100 B
b111 G
b10 F
0'
00
#51000
1'
b1111001101000010 %
b1111001101000010 A
b1111001101000010 Q
10
#52000
b10101 (
b10101 5
b10101 N
b10101 /
b10101 3
b10101 B
b1000 G
b11 F
0'
00
#53000
1'
b10111111100011 %
b10111111100011 A
b10111111100011 Q
10
#54000
b0 $
b0 P
b0 T
b0 +
b0 C
b0 S
b10xxxxxxxxxxxxxx E
b0 G
0'
00
#55000
10
#56000
b1 $
b1 P
b1 T
b1001100 (
b1001100 5
b1001100 N
b1 8
b10 >
b11 <
1!
b1001100 .
b1001100 4
b1001100 6
0*
b0xxxxxxxxxxxxxx E
1)
b1101111111100001 &
b1101111111100001 D
b1101111111100001 O
b1110110111101111 J
b1 K
b1000 L
00
#57000
10
#58000
b10 F
b0 H
b1xxxxxxxxxxxxxx E
b10101 (
b10101 5
b10101 N
b0 $
b0 P
b0 T
b10 #
b10 9
b10 ?
b0 8
1*
0!
0)
00
#59000
10
#60000
b10 $
b10 P
b10 T
b10 +
b10 C
b10 S
00
#61000
1'
10
#62000
b11 (
b11 5
b11 N
b11 /
b11 3
b11 B
b1 G
b11 F
0'
00
#63000
1'
b0 %
b0 A
b0 Q
10
#64000
b100 (
b100 5
b100 N
b100 /
b100 3
b100 B
b10 G
b100 F
0'
00
#65000
1'
10
#66000
b1011 (
b1011 5
b1011 N
b1011 /
b1011 3
b1011 B
b11 G
b10 F
b1 H
0'
00
#67000
1'
b10001111101101 %
b10001111101101 A
b10001111101101 Q
10
#68000
b1100 (
b1100 5
b1100 N
b1100 /
b1100 3
b1100 B
b100 G
b11 F
0'
00
#69000
1'
b1110110111101111 %
b1110110111101111 A
b1110110111101111 Q
10
#70000
b1101 (
b1101 5
b1101 N
b1101 /
b1101 3
b1101 B
b101 G
b100 F
0'
00
#71000
1'
b1110111011011111 %
b1110111011011111 A
b1110111011011111 Q
10
#72000
b10100 (
b10100 5
b10100 N
b10100 /
b10100 3
b10100 B
b110 G
b10 F
b10 H
0'
00
#73000
1'
b1111001101000010 %
b1111001101000010 A
b1111001101000010 Q
10
#74000
b10101 (
b10101 5
b10101 N
b10101 /
b10101 3
b10101 B
b111 G
b11 F
0'
00
#75000
1'
b10111111100011 %
b10111111100011 A
b10111111100011 Q
10
#76000
b10110 (
b10110 5
b10110 N
b10110 /
b10110 3
b10110 B
b1000 G
b100 F
0'
00
#77000
1'
b1000111101010 %
b1000111101010 A
b1000111101010 Q
10
#78000
b0 $
b0 P
b0 T
b0 +
b0 C
b0 S
b10xxxxxxxxxxxxxx E
b0 G
0'
00
#79000
10
#80000
b1 $
b1 P
b1 T
b1001101 (
b1001101 5
b1001101 N
b1 8
b11 >
b100 <
1!
b1001101 .
b1001101 4
b1001101 6
0*
b0xxxxxxxxxxxxxx E
1)
b10111111100011 &
b10111111100011 D
b10111111100011 O
b1110110111101111 J
b1 K
b1000 L
00
#81000
10
#82000
b11 F
b0 H
b1xxxxxxxxxxxxxx E
b10110 (
b10110 5
b10110 N
b0 $
b0 P
b0 T
b11 #
b11 9
b11 ?
b0 8
1*
0!
0)
00
#83000
10
#84000
b10 $
b10 P
b10 T
b10 +
b10 C
b10 S
00
#85000
1'
10
#86000
b100 (
b100 5
b100 N
b100 /
b100 3
b100 B
b1 G
b100 F
0'
00
#87000
1'
b0 %
b0 A
b0 Q
10
#88000
b101 (
b101 5
b101 N
b101 /
b101 3
b101 B
b10 G
b101 F
0'
00
#89000
1'
10
#90000
b1100 (
b1100 5
b1100 N
b1100 /
b1100 3
b1100 B
b11 G
b11 F
b1 H
0'
00
#91000
1'
b1110110111101111 %
b1110110111101111 A
b1110110111101111 Q
10
#92000
b1101 (
b1101 5
b1101 N
b1101 /
b1101 3
b1101 B
b100 G
b100 F
0'
00
#93000
1'
b1110111011011111 %
b1110111011011111 A
b1110111011011111 Q
10
#94000
b1110 (
b1110 5
b1110 N
b1110 /
b1110 3
b1110 B
b101 G
b101 F
0'
00
#95000
1'
b1110111000100011 %
b1110111000100011 A
b1110111000100011 Q
10
#96000
b10101 (
b10101 5
b10101 N
b10101 /
b10101 3
b10101 B
b110 G
b11 F
b10 H
0'
00
#97000
1'
b10111111100011 %
b10111111100011 A
b10111111100011 Q
10
#98000
b10110 (
b10110 5
b10110 N
b10110 /
b10110 3
b10110 B
b111 G
b100 F
0'
00
#99000
1'
b1000111101010 %
b1000111101010 A
b1000111101010 Q
10
#100000
b10111 (
b10111 5
b10111 N
b10111 /
b10111 3
b10111 B
b1000 G
b101 F
0'
00
#101000
1'
b1010101111000011 %
b1010101111000011 A
b1010101111000011 Q
10
#102000
b0 $
b0 P
b0 T
b0 +
b0 C
b0 S
b10xxxxxxxxxxxxxx E
b0 G
0'
00
#103000
10
#104000
b1 $
b1 P
b1 T
b1001110 (
b1001110 5
b1001110 N
b1 8
b100 >
b101 <
1!
b1001110 .
b1001110 4
b1001110 6
0*
b0xxxxxxxxxxxxxx E
1)
b10111111100011 J
b1 K
b1000 L
00
#105000
10
#106000
b100 F
b0 H
b1xxxxxxxxxxxxxx E
b10111 (
b10111 5
b10111 N
b0 $
b0 P
b0 T
b100 #
b100 9
b100 ?
b0 8
1*
0!
0)
00
#107000
10
#108000
b10 $
b10 P
b10 T
b10 +
b10 C
b10 S
00
#109000
1'
10
#110000
b101 (
b101 5
b101 N
b101 /
b101 3
b101 B
b1 G
b101 F
0'
00
#111000
1'
b0 %
b0 A
b0 Q
10
#112000
b110 (
b110 5
b110 N
b110 /
b110 3
b110 B
b10 G
b110 F
0'
00
#113000
1'
10
#114000
b1101 (
b1101 5
b1101 N
b1101 /
b1101 3
b1101 B
b11 G
b100 F
b1 H
0'
00
#115000
1'
b1110111011011111 %
b1110111011011111 A
b1110111011011111 Q
10
#116000
b1110 (
b1110 5
b1110 N
b1110 /
b1110 3
b1110 B
b100 G
b101 F
0'
00
#117000
1'
b1110111000100011 %
b1110111000100011 A
b1110111000100011 Q
10
#118000
b1111 (
b1111 5
b1111 N
b1111 /
b1111 3
b1111 B
b101 G
b110 F
0'
00
#119000
1'
b11111011011110 %
b11111011011110 A
b11111011011110 Q
10
#120000
b10110 (
b10110 5
b10110 N
b10110 /
b10110 3
b10110 B
b110 G
b100 F
b10 H
0'
00
#121000
1'
b1000111101010 %
b1000111101010 A
b1000111101010 Q
10
#122000
b10111 (
b10111 5
b10111 N
b10111 /
b10111 3
b10111 B
b111 G
b101 F
0'
00
#123000
1'
b1010101111000011 %
b1010101111000011 A
b1010101111000011 Q
10
#124000
b11000 (
b11000 5
b11000 N
b11000 /
b11000 3
b11000 B
b1000 G
b110 F
0'
00
