Verilog_V1/Median_Filter.v
/////////////////////////////////////////////////////////////////////////////
//
// @brief: Verilog Implementatin of the Median Filter: This Module
//			Is final stage in implementing the median filter.
//
// @version: 0.0.1
// @Date: 09/05/2024
// @filename: Median_Filter.v
//
//
// @authors: 
///////////////////////////////////////////////////////////////////////////////////////////


module Median_Filter(
/////////////////////Control Ports///////////////////////////////////////////////

Filter_CLK,Filter_RST, 

///////////////////Index_Tracker Interfacing Ports///////////////////////////////

 Filter_EN,Filter_sROW, Filter_sCOL, Filter_OUT, Filter_FILTDRDY,

 ///////////////////Memory Interfacing Ports////////////////////////////////////

 Filter_MEMDR, Filter_MEMADDR, Filter_MEMREAD, Filter_MEMDRDY

 );

 //------------------------------------------------------------------------------------------------//
 //								MEDIAN FILTER PARAMETERS
 //------------------------------------------------------------------------------------------------//

parameter WINDOW_SIZE = 3; //Defaults to window size fo 3x3
parameter DATA_WIDTH = 24; // defult RGB pixel width
parameter BUS_WIDTH = 32; //same as Memory.v module
parameter IMG_WIDTH = 512;

//----------------------------------------------------------------------------------------------------------------//
//								FILTER PORTS
//----------------------------------------------------------------------------------------------------------------//

//Control Ports

input Filter_RST ; // Filter reset line.

input Filter_CLK; // Filter clock signal (for synchronized operations)

//Index_Tracker Interfacning ports

input [BUS_WIDTH-1:0] Filter_sROW; // Index of the row number where the filter window starts
input [BUS_WIDTH-1:0] Filter_sCOL; // Index of the column number where the window starts
input Filter_EN; // Filter Enable Line: image processed only when this line is HIGH
output reg [DATA_WIDTH-1:0] Filter_OUT; // Resultig Filter pixel of the window.
output reg Filter_FILTDRDY; // Signaling line that a single pixel has been processed.

//Memory Interfacing ports

input [DATA_WIDTH-1:0] Filter_MEMDR; // Pixel Data from the memory: this is the pixel within the filter window.
input Filter_MEMDRDY; // Memory Data Ready Line.
output reg [BUS_WIDTH-1:0] Filter_MEMADDR;
output reg [1:0] Filter_MEMREAD;

/////////////////////////////////INTERNAL REGISTERS//////////////////////////////////////////////////////////

reg [15:0] Filter_SR; // Filter status Register
// Iterators
integer row;
integer col;
integer i;
reg started;
integer wind_indx; // keeps index of the window where insertion should be made

reg [DATA_WIDTH-1:0] window [0:WINDOW_SIZE*WINDOW_SIZE-1]; // Convolution window of the filter

////////////////////////////////////////////////////////////////////////////////////////////////////////////

//Function that sorts the elements in window buffer, uses bubble sort
function sortWindow(input integer mxm);
	reg [ DATA_WIDTH-1:0] temp;
	integer k, j ; // iterators
	begin
		for( k = 0;k< WINDOW_SIZE*WINDOW_SIZE-1; k= k+1) begin
			for(j=0; j < WINDOW_SIZE*WINDOW_SIZE-1-k; j= j+1) begin
				if(window[j] > window[j+1]) begin
					temp = window[j];
					window[j] = window[j+1];
					window[j+1] = temp;
				end
			end
		end
		sortWindow =0;
	end

endfunction


//////////////////////////////////////MODULE IMPLEMENTATION///////////////////////////////////////////////

always@(posedge Filter_CLK) begin		
		if(Filter_RST) begin
			row <=0;
			col <=0;
			i <=0;
			wind_indx <=0;
			for(wind_indx = 0; wind_indx < WINDOW_SIZE*WINDOW_SIZE ; wind_indx++) begin
				window[wind_indx] <=0;
			end
			Filter_OUT <=0;
			Filter_FILTDRDY <=0;
			Filter_MEMADDR <=0;
			Filter_MEMREAD <=0;
		end
end

//at the start of each window read request
always@(posedge Filter_EN) begin
	Filter_SR[15:14] <= 2'b01; // set mode to READ_WINDOW
	row <= Filter_sROW; // row number f the first pixel in the convolution window
	col <= Filter_sCOL; //
	Filter_MEMADDR <= row*IMG_WIDTH + col; // 
end

//Handle MEMORY DATA READY REQUESTS.

always@(negedge Filter_MEMDRDY) begin
	// Check to see if the  filter is still enabled
	if(Filter_EN==1 && Filter_SR[15:14] == 1) begin
		if(i>=WINDOW_SIZE*WINDOW_SIZE-1) begin
			i = 0; // reset the window size_tracker
			Filter_SR[15:14] = 2'b10; // set the status to 2: WINDW_READY: this propts for sorting and computation of the median
			Filter_MEMREAD = 0;
		end else begin
			//add the value the current index from the window:
			window[i] = Filter_MEMDR; // Read the data on the Memory Data Bus, and store it  in the window
			
			if((i+1)%(WINDOW_SIZE)==0 && i!=0) begin
				row = row + 1;
				col = Filter_sCOL;
				i = i+1;
			end else begin
				col = col+1;
				i = i+1;
			end
			Filter_MEMADDR= row*IMG_WIDTH + col; //get address of the next pixel.
		end
	end // otherwise igore this trigger it isn't meant for you
end

always@(negedge Filter_CLK) begin

	if(Filter_SR[15:14] == 1 && Filter_EN ==1) begin
		Filter_MEMREAD = 2; // Promt for memory read.
	end 

	else if(Filter_SR[15:14] == 2) begin
		//Sort the window
		i=sortWindow(0); // THis function will sort the window.
		//when obtain the 
		Filter_OUT = window[(WINDOW_SIZE*WINDOW_SIZE)/2]; // Median  is at the middle of the window.
		Filter_FILTDRDY = 1; // set filter data ready.
		Filter_SR[15:14] = 0; // set the status to WAIT_FOR_NEW_WINDOW  or IDLE
		Filter_MEMREAD = 0;
	end else if(Filter_SR[15:14] ==0) begin

		Filter_FILTDRDY = 0;

	end

end


endmodule

Verilog_V1/Memory.v
//////////////////////////////////////////////////////////////////////////////////////////////////
//																								
// @brief: Memory module that stores image pixels during porcessing		
// Date: 08/05/2024											
// Version: v0													
// Filename: Memory.v														
//														
//Project: FPGA Implementation of a median filter							
//Authors:											
//															
//////////////////////////////////////////////////////////////////////////////////////////////////

`timescale 1ns/1ps

module Memory(Mem_CLK, Mem_RST, Mem_RW, Mem_ADDR, Mem_IDR, Mem_ODR, Mem_DRDY);

//----------------------------------------------------------------------------------------------//
//				MEMORY PARAMETERS                            
//----------------------------------------------------------------------------------------------//

parameter DATA_WIDTH = 24; // Defualts to 24-bits ( for threee chanel image)

parameter DEPTH = 512*512; // Defaults to 512*512 pixels ( maximum size of images to be processed)

parameter ADDR_WIDTH = 32; //Width of the address, defaults to 32-bit bus address

parameter FILENAME = "test_hex.txt";

//----------------------------------------------------------------------------------------------//
//				MEMORY PORT DECLARATION															
//----------------------------------------------------------------------------------------------//
 input Mem_CLK; //Input Clock
 input Mem_RST; //Reset line
 input [1:0] Mem_RW; // read or write selection line
 input [DATA_WIDTH-1:0] Mem_IDR; // Memory Input Data ( the Write Data)
 output  reg [DATA_WIDTH-1:0] Mem_ODR; // Memory Output Data ( read data)
 output reg Mem_DRDY; // Memory Data ready flag.
 input [ADDR_WIDTH-1:0] Mem_ADDR;

//----------------------------------------------------------------------------------------------//
//							MEMORY INTERNAL REGISTERS			
//----------------------------------------------------------------------------------------------//

reg [DATA_WIDTH-1:0] MEMORY [0:DEPTH-1]; //MEMORY  BLOCK

//----------------------------------------------------------------------------------------------//
///						MODULE IMPLEMENTATION
//----------------------------------------------------------------------------------------------//

////////////////////////////////ITERATIRS/////////////////////////////////////////////////////////

integer iter;

always@(posedge Mem_CLK) begin
	
	//Reset
	if(Mem_RST) begin
		$readmemh(FILENAME,MEMORY); //reads Data from Memory.
		Mem_ODR <= 0;
		Mem_DRDY <=0;
	end else if(Mem_RW == 2'b01) begin
		MEMORY[Mem_ADDR] <= Mem_IDR;
	end else if(Mem_RW == 2'b10) begin
		Mem_ODR<= MEMORY[Mem_ADDR];
		Mem_DRDY<= 1;
	end else if(Mem_RW == 2'b11) begin
		$readmemh(FILENAME,MEMORY); //reads Data from Memory.
		Mem_DRDY <= 1; //Notify that Data Is Ready(has been read)
	end

end

//Clear the ready flag on the next falling edge
always@(negedge Mem_CLK) begin
	Mem_DRDY <= 0;
end

endmodule

Verilog_V1/windowReadTB.v
//Testbench for Median_Filter module

`timescale 1ns/1ps

module windowReadTB();

//parameters

parameter WINDOW_WIDTH = 3;
parameter DATA_DEPTH = 49;
parameter DATA_WIDTH = 16;
parameter IMG_WIDTH = 7;
parameter BUS_WIDTH = 8;

// varianbles

reg clk, rst;
wire [1:0] rw;
wire [BUS_WIDTH-1:0]mem_addr;
wire [DATA_WIDTH-1:0] mem_odata;
wire [DATA_WIDTH-1:0] mem_idata;
wire mem_drdy;

reg [BUS_WIDTH-1:0] sROW;
reg filt_en;
reg [BUS_WIDTH-1:0] sCOL;

wire [DATA_WIDTH-1:0] filter_out;
wire filt_rdy;
//module Memory(Mem_CLK, Mem_RST, Mem_RW, Mem_ADDR, Mem_IDR, Mem_ODR, Mem_DRDY);
//Instatiate the memory module.

Memory #(.DATA_WIDTH(DATA_WIDTH), .ADDR_WIDTH(BUS_WIDTH), .DEPTH(DATA_DEPTH)) memory
(clk, rst, rw, mem_addr, mem_idata, mem_odata, mem_drdy);

//Instantiate the Median_Filter module

Median_Filter #(.WINDOW_SIZE(WINDOW_WIDTH), .DATA_WIDTH(DATA_WIDTH), .BUS_WIDTH(BUS_WIDTH), .IMG_WIDTH(IMG_WIDTH))
filter(clk,rst,filt_en, sROW, sCOL, filter_out, filt_rdy,mem_odata, mem_addr,rw,mem_drdy);



initial begin

	$dumpfile("windowReadDump.vcd");
	$dumpvars(0, windowReadTB);
	$monitor($time,"\tCLK:%b  RST:%b  FILTER_ENABLE:%b ADDR: %x  MEMDATA: %x  FiltOUT: %x  MemRDY:%b FiltRDY:%b",
	
	clk,rst,filt_en,mem_addr,mem_odata,filter_out, mem_drdy, filt_rdy);
	
	clk =0; rst=0; filt_en=0; sROW=3; sCOL =2;

	// reset the modules
	#4 rst = 1;
	#2 rst = 0; 
	#3 filt_en = 1; // enable the window
	#50 $finish; 
end

always begin
	#1 clk = ~clk;
end
endmodule

Verilog_V1/windowReadDump.vcd
$date
	Sat May 11 17:54:01 2024
$end
$version
	Icarus Verilog
$end
$timescale
	1ps
$end
$scope module windowReadTB $end
$var wire 16 ! mem_idata [15:0] $end
$var wire 2 " rw [1:0] $end
$var wire 16 # mem_odata [15:0] $end
$var wire 1 $ mem_drdy $end
$var wire 8 % mem_addr [7:0] $end
$var wire 16 & filter_out [15:0] $end
$var wire 1 ' filt_rdy $end
$var reg 1 ( clk $end
$var reg 1 ) filt_en $end
$var reg 1 * rst $end
$var reg 8 + sCOL [7:0] $end
$var reg 8 , sROW [7:0] $end
$scope module filter $end
$var wire 1 ( Filter_CLK $end
$var wire 1 ) Filter_EN $end
$var wire 1 * Filter_RST $end
$var wire 8 - Filter_sCOL [7:0] $end
$var wire 8 . Filter_sROW [7:0] $end
$var wire 1 $ Filter_MEMDRDY $end
$var wire 16 / Filter_MEMDR [15:0] $end
$var reg 1 ' Filter_FILTDRDY $end
$var reg 8 0 Filter_MEMADDR [7:0] $end
$var reg 2 1 Filter_MEMREAD [1:0] $end
$var reg 16 2 Filter_OUT [15:0] $end
$var reg 16 3 Filter_SR [15:0] $end
$var integer 32 4 col [31:0] $end
$var integer 32 5 i [31:0] $end
$var integer 32 6 row [31:0] $end
$var integer 32 7 wind_indx [31:0] $end
$scope function sortWindow $end
$var reg 16 8 temp [15:0] $end
$var integer 32 9 j [31:0] $end
$var integer 32 : k [31:0] $end
$var integer 32 ; mxm [31:0] $end
$upscope $end
$upscope $end
$scope module memory $end
$var wire 8 < Mem_ADDR [7:0] $end
$var wire 1 ( Mem_CLK $end
$var wire 16 = Mem_IDR [15:0] $end
$var wire 1 * Mem_RST $end
$var wire 2 > Mem_RW [1:0] $end
$var reg 1 $ Mem_DRDY $end
$var reg 16 ? Mem_ODR [15:0] $end
$upscope $end
$upscope $end
$enddefinitions $end
#0
$dumpvars
bx ?
bx >
bz =
bx <
bx ;
bx :
bx 9
bx 8
bx 7
bx 6
bx 5
bx 4
bx 3
bx 2
bx 1
bx 0
bx /
b11 .
b10 -
b11 ,
b10 +
0*
0)
0(
x'
bx &
bx %
0$
bx #
bx "
bz !
$end
#1000
1(
#2000
0(
#3000
1(
#4000
0(
1*
#5000
b0 #
b0 /
b0 ?
b0 "
b0 1
b0 >
b0 %
b0 0
b0 <
0'
b0 &
b0 2
b0 5
b0 4
b0 6
b0 7
1(
#6000
0(
0*
#7000
1(
#8000
0(
#9000
1$
b10001111011110 #
b10001111011110 /
b10001111011110 ?
b1xxxxxxxxxxxxxx 3
b10 "
b10 1
b10 >
b10111 %
b10111 0
b10111 <
b10 4
b11 6
1(
1)
#10000
b11000 %
b11000 0
b11000 <
b1 5
b11 4
0$
0(
#11000
1$
b1110111111111110 #
b1110111111111110 /
b1110111111111110 ?
1(
#12000
b11001 %
b11001 0
b11001 <
b10 5
b100 4
0$
0(
#13000
1$
b1001000100011 #
b1001000100011 /
b1001000100011 ?
1(
#14000
b11110 %
b11110 0
b11110 <
b11 5
b10 4
b100 6
0$
0(
#15000
1$
b101011011110011 #
b101011011110011 /
b101011011110011 ?
1(
#16000
b11111 %
b11111 0
b11111 <
b100 5
b11 4
0$
0(
#17000
1$
b1111111111100010 #
b1111111111100010 /
b1111111111100010 ?
1(
#18000
b100000 %
b100000 0
b100000 <
b101 5
b100 4
0$
0(
#19000
1$
b1111111010101101 #
b1111111010101101 /
b1111111010101101 ?
1(
#20000
b100101 %
b100101 0
b100101 <
b110 5
b10 4
b101 6
0$
0(
#21000
1$
b1100101111001101 #
b1100101111001101 /
b1100101111001101 ?
1(
#22000
b100110 %
b100110 0
b100110 <
b111 5
b11 4
0$
0(
#23000
1$
b1101110011011101 #
b1101110011011101 /
b1101110011011101 ?
1(
#24000
b100111 %
b100111 0
b100111 <
b1000 5
b100 4
0$
0(
#25000
1$
b1010110111101101 #
b1010110111101101 /
b1010110111101101 ?
1(
#26000
b0 "
b0 1
b0 >
b10xxxxxxxxxxxxxx 3
b0 5
0$
0(
#27000
1(
#28000
b0xxxxxxxxxxxxxx 3
1'
b1100101111001101 &
b1100101111001101 2
b1001000100011 8
b1 9
b1000 :
b0 ;
0(
#29000
1(
#30000
0'
0(
