Verilog_V1/Window_Reader.v
/////////////////////////////////////////////////////////////////////////////////////////////
//
//@brief: Read the pixels in a window currently processed by the median filter from memory
//@date: 08/05/2024
//@version: 0.0.1
//
//filename: Window_Reader.v
//@authors:
//
/////////////////////////////////////////////////////////////////////////////////////////////


module Window_Reader( Wind_Rset, Wind_Rstrt, Wind_Cstrt,Wind_En,Wind_MemData,Wind_DRDY,
Wind_MemAddr,Wind_Ren, Wind_Data,Wind_RDY);

//------------------------------------------------------------------------------------------
//					MODULE PARAMETERS					
//------------------------------------------------------------------------------------------

parameter WINDOW_SIZE = 3; //Defaults to window size fo 3x3
parameter DATA_WIDTH = 24; // defult RGB pixel width
parameter BUS_WIDTH = 32; //same as Memory.v module
parameter IMG_WIDTH = 512;
//-----------------------------------------------------------------------------------------
//				MODULE PORT DECLARATIONS				  
//-----------------------------------------------------------------------------------------
input Wind_Rset; //Reset line
input [BUS_WIDTH-1:0] Wind_Rstrt; //Row number where the window starts
input [BUS_WIDTH-1:0] Wind_Cstrt; //Column number where the windw start
input Wind_En; //Enable line for the module (keep this line while reading in undergoing)
input [DATA_WIDTH-1:0] Wind_MemData;// Data read from the memory
input Wind_DRDY;// Signal indicating when Win_MemData is ready
output reg [BUS_WIDTH-1:0] Wind_MemAddr; // Address where to read the data pixels
output reg [1:0] Wind_Ren; // Read Enable bit to memory
output reg Wind_RDY; //signal to indicate that window data is ready
output reg [(DATA_WIDTH*WINDOW_SIZE*WINDOW_SIZE)-1:0] Wind_Data;

//------------------------------------------------------------------------------------------
//				MODULE IMPLEMENTATION					
//------------------------------------------------------------------------------------------

//Iterators/////////////////////////////////////////////////////////////////////////////////

integer row;
integer col;
integer i;
integer tot_window_size;
always@(posedge Wind_Rset) begin
	Wind_MemAddr <= 0;
	Wind_Ren <=0;
	Wind_RDY<=0;
	Wind_Data<=0;
	i <=0;
	row <=0;
	tot_window_size <= WINDOW_SIZE*WINDOW_SIZE*DATA_WIDTH;
	col <=0;
end


always@(posedge Wind_En) begin
	row = Wind_Rstrt;
	col = Wind_Cstrt;
	Wind_MemAddr = row*WINDOW_SIZE+col; //Build the address where the start pixel is located
	Wind_Ren = 2'b10; // Enable Read
end

//Wind_DRDY is ready flag sent by the Memory module (it will occur at the rising edge of the clock)
always@(negedge Wind_DRDY) begin
	Wind_Ren = 2'b00; //reset window ready to 0
	if(i>=WINDOW_SIZE*WINDOW_SIZE) begin
		i = 0;
		Wind_RDY=1'b1;
	end else begin
		if(Wind_En) begin
			Wind_Data[tot_window_size-1-(DATA_WIDTH*i)-:DATA_WIDTH] = Wind_MemData;
		//increment iterators
			if(i%(WINDOW_SIZE-1)==0 && i!=0) begin
				row = row + 1;
				col = Wind_Cstrt;
				i = i+1;
			end else begin
				col = col+1;
				i = i+1;
			end
			Wind_MemAddr= row*IMG_WIDTH + col; //get address of the next pixel.
			Wind_Ren =2'b10; // Enable Read Again
		end
	end
end


always@(negedge Wind_En) begin
	Wind_RDY <= 0;
end
endmodule

Verilog_V1/Memory.v
//////////////////////////////////////////////////////////////////////////////////////////////////
//																								
// @brief: Memory module that stores image pixels during porcessing		
// Date: 08/05/2024											
// Version: v0													
// Filename: Memory.v														
//														
//Project: FPGA Implementation of a median filter							
//Authors:											
//															
//////////////////////////////////////////////////////////////////////////////////////////////////

`timescale 1ns/1ps

module Memory(Mem_CLK, Mem_RST, Mem_RW, Mem_ADDR, Mem_IDR, Mem_ODR, Mem_DRDY);

//----------------------------------------------------------------------------------------------//
//				MEMORY PARAMETERS                            
//----------------------------------------------------------------------------------------------//

parameter DATA_WIDTH = 24; // Defualts to 24-bits ( for threee chanel image)

parameter DEPTH = 512*512; // Defaults to 512*512 pixels ( maximum size of images to be processed)

parameter ADDR_WIDTH = 32; //Width of the address, defaults to 32-bit bus address

parameter FILENAME = "test_hex.txt";

//----------------------------------------------------------------------------------------------//
//				MEMORY PORT DECLARATION															
//----------------------------------------------------------------------------------------------//
 input Mem_CLK; //Input Clock
 input Mem_RST; //Reset line
 input [1:0] Mem_RW; // read or write selection line
 input [DATA_WIDTH-1:0] Mem_IDR; // Memory Input Data ( the Write Data)
 output  reg [DATA_WIDTH-1:0] Mem_ODR; // Memory Output Data ( read data)
 output reg Mem_DRDY; // Memory Data ready flag.
 input [ADDR_WIDTH-1:0] Mem_ADDR;

//----------------------------------------------------------------------------------------------//
//							MEMORY INTERNAL REGISTERS			
//----------------------------------------------------------------------------------------------//

reg [DATA_WIDTH-1:0] MEMORY [0:DEPTH-1]; //MEMORY  BLOCK

//----------------------------------------------------------------------------------------------//
///						MODULE IMPLEMENTATION
//----------------------------------------------------------------------------------------------//

////////////////////////////////ITERATIRS/////////////////////////////////////////////////////////

integer iter;

always@(posedge Mem_CLK) begin
	
	//Reset
	if(Mem_RST) begin
		$readmemh(FILENAME,MEMORY); //reads Data from Memory.
		Mem_ODR <= 0;
		Mem_DRDY <=0;
	end else if(Mem_RW == 2'b01) begin
		MEMORY[Mem_ADDR] <= Mem_IDR;
	end else if(Mem_RW == 2'b10) begin
		Mem_ODR<= MEMORY[Mem_ADDR];
		Mem_DRDY<= 1;
	end else if(Mem_RW == 2'b11) begin
		$readmemh(FILENAME,MEMORY); //reads Data from Memory.
		Mem_DRDY <= 1; //Notify that Data Is Ready(has been read)
	end

end

//Clear the ready flag on the next falling edge
always@(negedge Mem_CLK) begin
	Mem_DRDY <= 0;
end

endmodule

Verilog_V1/memTB.v
`timescale 1ns/1ps
module testbench();

	parameter DATA_WIDTH = 8'h10;
	parameter DEPTH = 49;
	parameter BUS_WIDTH = 8;
	parameter WINDOW = 3;
	reg clk, rst;
	wire [1:0] rw;
	reg [DATA_WIDTH-1:0] inputData;
	wire rdy;
	wire [BUS_WIDTH-1:0]  mem_addr;
	wire [DATA_WIDTH-1:0] outputData;
	wire [DATA_WIDTH*WINDOW*WINDOW-1:0] window;
	reg  [1:0] read;
	//module Memory(Mem_CLK, Mem_RST, Mem_RW, Mem_ADDR, Mem_IDR, Mem_ODR, Mem_DRDY);
	
	//Instantiation

	reg [BUS_WIDTH-1:0] rStart;
	reg [BUS_WIDTH-1:0] cStart;
	reg wind_enable;
	wire window_ready;

	Memory #(DATA_WIDTH, DEPTH, BUS_WIDTH) mem_inst(clk,rst,rw,mem_addr,inputData,outputData,rdy);

	integer iter;

	//module Window_Reader( Wind_Rset, Wind_Rstrt, Wind_Cstrt,Wind_En,Wind_MemData,Wind_DRDY,
	//Wind_MemAddr,Wind_Ren, Wind_Data,Wind_RDY);

	Window_Reader #(.WINDOW_SIZE(WINDOW),.IMG_WIDTH(7),.BUS_WIDTH(BUS_WIDTH),.DATA_WIDTH(DATA_WIDTH)) 
	winder_reader (rst,rStart,cStart,wind_enable,outputData,rdy,mem_addr,rw,window,window_ready);
	initial begin

		$dumpfile("windowTest.vcd");
		$dumpvars(0, testbench);
		$monitor($time,"\tClk:%d RST:%b RW:%b window_enable:%b window_rdy:%b  Row:%x Col:%x Data:%x Addr:%x Window:%x",
		clk,rst,rw,wind_enable,window_ready,rStart,cStart,outputData,mem_addr,window);
		rStart =0;
		cStart = 0;
		wind_enable =0;
		rst =0; 
		clk = 0;
		#4 rst = 1;
		#2 rst =0;
		//rw = 3;
		#4 wind_enable = 1;
		#100 $finish ;

	end

	always@(posedge window_ready) begin
		#2 wind_enable = 0;
	end
	always begin
		#1 clk = ~clk;
	end

endmodule

Verilog_V1/windowTest.vcd
$date
	Thu May  9 15:46:07 2024
$end
$version
	Icarus Verilog
$end
$timescale
	1ps
$end
$scope module testbench $end
$var wire 1 ! window_ready $end
$var wire 144 " window [143:0] $end
$var wire 2 # rw [1:0] $end
$var wire 1 $ rdy $end
$var wire 16 % outputData [15:0] $end
$var wire 8 & mem_addr [7:0] $end
$var reg 8 ' cStart [7:0] $end
$var reg 1 ( clk $end
$var reg 16 ) inputData [15:0] $end
$var reg 8 * rStart [7:0] $end
$var reg 1 + rst $end
$var reg 1 , wind_enable $end
$scope module mem_inst $end
$var wire 1 ( Mem_CLK $end
$var wire 16 - Mem_IDR [15:0] $end
$var wire 1 + Mem_RST $end
$var wire 2 . Mem_RW [1:0] $end
$var wire 8 / Mem_ADDR [7:0] $end
$var reg 1 $ Mem_DRDY $end
$var reg 16 0 Mem_ODR [15:0] $end
$upscope $end
$scope module winder_reader $end
$var wire 8 1 Wind_Cstrt [7:0] $end
$var wire 1 $ Wind_DRDY $end
$var wire 1 , Wind_En $end
$var wire 16 2 Wind_MemData [15:0] $end
$var wire 1 + Wind_Rset $end
$var wire 8 3 Wind_Rstrt [7:0] $end
$var reg 144 4 Wind_Data [143:0] $end
$var reg 8 5 Wind_MemAddr [7:0] $end
$var reg 1 ! Wind_RDY $end
$var reg 2 6 Wind_Ren [1:0] $end
$var integer 32 7 col [31:0] $end
$var integer 32 8 i [31:0] $end
$var integer 32 9 row [31:0] $end
$var integer 32 : tot_window_size [31:0] $end
$upscope $end
$upscope $end
$enddefinitions $end
#0
$dumpvars
bx :
bx 9
bx 8
bx 7
b0 6
bx 5
bx 4
b0 3
bx 2
b0 1
bx 0
bx /
b0 .
bx -
0,
0+
b0 *
bx )
0(
b0 '
bx &
bx %
0$
b0 #
bx "
0!
$end
#1000
1(
#2000
0(
#3000
1(
#4000
b0 7
b10010000 :
b0 9
b0 8
b0 "
b0 4
b0 &
b0 /
b0 5
0(
1+
#5000
b0 %
b0 0
b0 2
1(
#6000
0(
0+
#7000
1(
#8000
0(
#9000
1(
#10000
b10 #
b10 .
b10 6
0(
1,
#11000
1$
b1101111111100001 %
b1101111111100001 0
b1101111111100001 2
1(
#12000
b1 &
b1 /
b1 5
b1 8
b1 7
b110111111110000100000000000000000000000000000000000000000000000000000000000000000000000000000000000000000000000000000000000000000000000000000000 "
b110111111110000100000000000000000000000000000000000000000000000000000000000000000000000000000000000000000000000000000000000000000000000000000000 4
b10 #
b10 .
b10 6
0$
0(
#13000
1$
b10001111101101 %
b10001111101101 0
b10001111101101 2
1(
#14000
b10 &
b10 /
b10 5
b10 8
b10 7
b110111111110000100100011111011010000000000000000000000000000000000000000000000000000000000000000000000000000000000000000000000000000000000000000 "
b110111111110000100100011111011010000000000000000000000000000000000000000000000000000000000000000000000000000000000000000000000000000000000000000 4
b10 #
b10 .
b10 6
0$
0(
#15000
1$
b1110110111101111 %
b1110110111101111 0
b1110110111101111 2
1(
#16000
b111 &
b111 /
b111 5
b11 8
b0 7
b1 9
b110111111110000100100011111011011110110111101111000000000000000000000000000000000000000000000000000000000000000000000000000000000000000000000000 "
b110111111110000100100011111011011110110111101111000000000000000000000000000000000000000000000000000000000000000000000000000000000000000000000000 4
b10 #
b10 .
b10 6
0$
0(
#17000
1$
b11010001011111 %
b11010001011111 0
b11010001011111 2
1(
#18000
b1000 &
b1000 /
b1000 5
b100 8
b1 7
b110111111110000100100011111011011110110111101111001101000101111100000000000000000000000000000000000000000000000000000000000000000000000000000000 "
b110111111110000100100011111011011110110111101111001101000101111100000000000000000000000000000000000000000000000000000000000000000000000000000000 4
b10 #
b10 .
b10 6
0$
0(
#19000
1$
b1111001101000010 %
b1111001101000010 0
b1111001101000010 2
1(
#20000
b1110 &
b1110 /
b1110 5
b101 8
b0 7
b10 9
b110111111110000100100011111011011110110111101111001101000101111111110011010000100000000000000000000000000000000000000000000000000000000000000000 "
b110111111110000100100011111011011110110111101111001101000101111111110011010000100000000000000000000000000000000000000000000000000000000000000000 4
b10 #
b10 .
b10 6
0$
0(
#21000
1$
b1111111010100011 %
b1111111010100011 0
b1111111010100011 2
1(
#22000
b1111 &
b1111 /
b1111 5
b110 8
b1 7
b110111111110000100100011111011011110110111101111001101000101111111110011010000101111111010100011000000000000000000000000000000000000000000000000 "
b110111111110000100100011111011011110110111101111001101000101111111110011010000101111111010100011000000000000000000000000000000000000000000000000 4
b10 #
b10 .
b10 6
0$
0(
#23000
1$
b100101111 %
b100101111 0
b100101111 2
1(
#24000
b10101 &
b10101 /
b10101 5
b111 8
b0 7
b11 9
b110111111110000100100011111011011110110111101111001101000101111111110011010000101111111010100011000000010010111100000000000000000000000000000000 "
b110111111110000100100011111011011110110111101111001101000101111111110011010000101111111010100011000000010010111100000000000000000000000000000000 4
b10 #
b10 .
b10 6
0$
0(
#25000
1$
b1101111001000101 %
b1101111001000101 0
b1101111001000101 2
1(
#26000
b10110 &
b10110 /
b10110 5
b1000 8
b1 7
b110111111110000100100011111011011110110111101111001101000101111111110011010000101111111010100011000000010010111111011110010001010000000000000000 "
b110111111110000100100011111011011110110111101111001101000101111111110011010000101111111010100011000000010010111111011110010001010000000000000000 4
b10 #
b10 .
b10 6
0$
0(
#27000
1$
b10001111101110 %
b10001111101110 0
b10001111101110 2
1(
#28000
b11100 &
b11100 /
b11100 5
b1001 8
b0 7
b100 9
b110111111110000100100011111011011110110111101111001101000101111111110011010000101111111010100011000000010010111111011110010001010010001111101110 "
b110111111110000100100011111011011110110111101111001101000101111111110011010000101111111010100011000000010010111111011110010001010010001111101110 4
b10 #
b10 .
b10 6
0$
0(
#29000
1$
b10001111101111 %
b10001111101111 0
b10001111101111 2
1(
#30000
1!
b0 8
b0 #
b0 .
b0 6
0$
0(
#31000
1(
#32000
0!
0(
0,
